isopat/__init__.py
isopat/cli.py
isopat/core.py
isopat/io.py
isopat-3.0.0.dist-info/licenses/LICENSE
isopat-3.0.0.dist-info/METADATA
isopat-3.0.0.dist-info/WHEEL
isopat-3.0.0.dist-info/entry_points.txt
isopat-3.0.0.dist-info/top_level.txt
isopat-3.0.0.dist-info/RECORD
