Metadata-Version: 2.4
Name: isopat
Version: 3.0.0
Summary: Isotope pattern deconvolution for mass spectrometry in isotope labeling studies
Author-email: "Christian C. Gruber" <christian.gruber@innophore.com>, Wolfgang Kroutil <wolfgang.kroutil@uni-graz.at>
Maintainer-email: "Christian C. Gruber" <christian.gruber@innophore.com>
License-Expression: MIT
Project-URL: Homepage, https://github.com/christiangruber1234/IsoPat
Project-URL: Repository, https://github.com/christiangruber1234/IsoPat
Project-URL: Bug Tracker, https://github.com/christiangruber1234/IsoPat/issues
Keywords: mass spectrometry,isotope labeling,deconvolution,deuterium,stable isotopes,metabolomics,analytical chemistry
Classifier: Development Status :: 5 - Production/Stable
Classifier: Intended Audience :: Science/Research
Classifier: Operating System :: OS Independent
Classifier: Programming Language :: Python :: 3
Classifier: Programming Language :: Python :: 3.9
Classifier: Programming Language :: Python :: 3.10
Classifier: Programming Language :: Python :: 3.11
Classifier: Programming Language :: Python :: 3.12
Classifier: Topic :: Scientific/Engineering :: Chemistry
Classifier: Topic :: Scientific/Engineering :: Bio-Informatics
Requires-Python: >=3.9
License-File: LICENSE
Requires-Dist: numpy>=1.20.0
Provides-Extra: dev
Requires-Dist: pytest>=7.0; extra == "dev"
Requires-Dist: pytest-cov>=4.0; extra == "dev"
Requires-Dist: black>=23.0; extra == "dev"
Requires-Dist: ruff>=0.1.0; extra == "dev"
Provides-Extra: docs
Requires-Dist: sphinx>=6.0; extra == "docs"
Requires-Dist: sphinx-rtd-theme>=1.0; extra == "docs"
Dynamic: license-file
